PFAID/PFAID.py
pfaid-1.0.1.dist-info/METADATA
pfaid-1.0.1.dist-info/WHEEL
pfaid-1.0.1.dist-info/licenses/LICENSE
pfaid-1.0.1.dist-info/RECORD
