Metadata-Version: 2.4
Name: PFAID
Version: 1.0.1
Summary: a simple POC about a PFAID more info in the readme...
Project-URL: Homepage, https://github.com/WeDu-official/Time_diffz
Project-URL: Issues, https://github.com/WeDu-official/Time_diffz/issues
Author-email: WeDu-official <fplu.the.founder@gmail.com>
License-File: LICENSE
Classifier: Development Status :: 5 - Production/Stable
Classifier: Intended Audience :: Developers
Classifier: License :: OSI Approved :: MIT License
Classifier: Natural Language :: English
Classifier: Operating System :: POSIX :: Linux
Classifier: Programming Language :: Python :: 3.10
Classifier: Programming Language :: Python :: 3.11
Classifier: Programming Language :: Python :: 3.12
Classifier: Programming Language :: Python :: 3.13
Classifier: Programming Language :: Python :: Implementation
Classifier: Programming Language :: Python :: Implementation :: CPython
Classifier: Topic :: Scientific/Engineering :: Image Processing
Requires-Python: >=3.10
Requires-Dist: pillow==12.0.0
